{
  "siteInfo": {
    "name": "ConsultPro",
    "description": "Strategic Business Consulting Services",
    "logo": "ConsultPro"
  },
  "navigation": {
    "logo": "ConsultPro",
    "links": [
      { "text": "Home", "href": "/" },
      { "text": "Services", "href": "#services" },
      { "text": "About", "href": "#about" },
      { "text": "Contact", "href": "#contact" }
    ]
  },
  "hero": {
    "title": "Strategic Solutions for Business Growth",
    "subtitle": "Transform your business with expert consulting services",
    "cta": "Get Started",
    "backgroundImage": "/hero-bg.jpg"
  },
  "services": {
    "title": "Our Services",
    "subtitle": "Comprehensive solutions tailored to your needs",
    "items": [
      {
        "title": "Strategy Consulting",
        "description": "Develop winning strategies for sustainable growth",
        "icon": "BarChart"
      },
      {
        "title": "Digital Transformation",
        "description": "Navigate the digital landscape with confidence",
        "icon": "Laptop"
      },
      {
        "title": "Operations Excellence",
        "description": "Optimize processes for maximum efficiency",
        "icon": "Settings"
      },
      {
        "title": "Financial Advisory",
        "description": "Make informed decisions with expert financial guidance",
        "icon": "DollarSign"
      }
    ]
  },
  "stats": [
    { "number": "500+", "label": "Clients Served" },
    { "number": "95%", "label": "Success Rate" },
    { "number": "50+", "label": "Expert Consultants" },
    { "number": "20+", "label": "Years Experience" }
  ],
  "testimonials": [
    {
      "quote": "ConsultPro transformed our business with their strategic insights.",
      "author": "Sarah Johnson",
      "position": "CEO, TechStart Inc."
    },
    {
      "quote": "The team's expertise helped us achieve record growth.",
      "author": "Michael Chen",
      "position": "Director, Global Solutions"
    },
    {
      "quote": "Outstanding service and remarkable results.",
      "author": "Emma Williams",
      "position": "COO, Innovation Labs"
    }
  ]
}